earthpy/__init__.py
earthpy/clip.py
earthpy/io.py
earthpy/mask.py
earthpy/plot.py
earthpy/spatial.py
earthpy/example-data/blue.tif
earthpy/example-data/colorado-counties.geojson
earthpy/example-data/colorado-glaciers.geojson
earthpy/example-data/continental-div-trail.geojson
earthpy/example-data/epsg.json
earthpy/example-data/green.tif
earthpy/example-data/red.tif
earthpy/example-data/rmnp-dem.tif
earthpy/example-data/rmnp-rgb.tif
earthpy/example-data/rmnp.dbf
earthpy/example-data/rmnp.prj
earthpy/example-data/rmnp.shp
earthpy/example-data/rmnp.shx
earthpy-0.9.4.dist-info/LICENSE
earthpy-0.9.4.dist-info/METADATA
earthpy-0.9.4.dist-info/WHEEL
earthpy-0.9.4.dist-info/top_level.txt
earthpy-0.9.4.dist-info/RECORD
